{"file:///d%3A/%E4%BC%9A%E8%AE%AE%E5%AE%A4%E9%A2%84%E7%BA%A6%E7%B3%BB%E7%BB%9F/mini/sitemap.json":{"language":"JSON","code":7,"comment":0,"blank":0},"file:///d%3A/%E4%BC%9A%E8%AE%AE%E5%AE%A4%E9%A2%84%E7%BA%A6%E7%B3%BB%E7%BB%9F/mini/utils/util.js":{"language":"JavaScript","code":16,"comment":0,"blank":4},"file:///d%3A/%E4%BC%9A%E8%AE%AE%E5%AE%A4%E9%A2%84%E7%BA%A6%E7%B3%BB%E7%BB%9F/mini/project.private.config.json":{"language":"JSON","code":129,"comment":0,"blank":0},"file:///d%3A/%E4%BC%9A%E8%AE%AE%E5%AE%A4%E9%A2%84%E7%BA%A6%E7%B3%BB%E7%BB%9F/mini/.idea/modules.xml":{"language":"XML","code":8,"comment":0,"blank":0},"file:///d%3A/%E4%BC%9A%E8%AE%AE%E5%AE%A4%E9%A2%84%E7%BA%A6%E7%B3%BB%E7%BB%9F/mini/package-lock.json":{"language":"JSON","code":13,"comment":0,"blank":1},"file:///d%3A/%E4%BC%9A%E8%AE%AE%E5%AE%A4%E9%A2%84%E7%BA%A6%E7%B3%BB%E7%BB%9F/mini/project.config.json":{"language":"JSON","code":75,"comment":0,"blank":0},"file:///d%3A/%E4%BC%9A%E8%AE%AE%E5%AE%A4%E9%A2%84%E7%BA%A6%E7%B3%BB%E7%BB%9F/mini/app.json":{"language":"JSON","code":35,"comment":0,"blank":0},"file:///d%3A/%E4%BC%9A%E8%AE%AE%E5%AE%A4%E9%A2%84%E7%BA%A6%E7%B3%BB%E7%BB%9F/mini/app.wxss":{"language":"CSS","code":13,"comment":15,"blank":3},"file:///d%3A/%E4%BC%9A%E8%AE%AE%E5%AE%A4%E9%A2%84%E7%BA%A6%E7%B3%BB%E7%BB%9F/mini/data/%E6%95%B0%E6%8D%AE2.json":{"language":"JSON","code":2,"comment":0,"blank":1},"file:///d%3A/%E4%BC%9A%E8%AE%AE%E5%AE%A4%E9%A2%84%E7%BA%A6%E7%B3%BB%E7%BB%9F/mini/pages/roomDetail2/roomDetail2.json":{"language":"JSON","code":5,"comment":0,"blank":0},"file:///d%3A/%E4%BC%9A%E8%AE%AE%E5%AE%A4%E9%A2%84%E7%BA%A6%E7%B3%BB%E7%BB%9F/mini/pages/handleEmployee/handleEmployee.wxml":{"language":"wxml","code":95,"comment":30,"blank":0},"file:///d%3A/%E4%BC%9A%E8%AE%AE%E5%AE%A4%E9%A2%84%E7%BA%A6%E7%B3%BB%E7%BB%9F/mini/pages/roomDetail2/roomDetail2.wxml":{"language":"wxml","code":100,"comment":19,"blank":0},"file:///d%3A/%E4%BC%9A%E8%AE%AE%E5%AE%A4%E9%A2%84%E7%BA%A6%E7%B3%BB%E7%BB%9F/mini/pages/handleEmployee/handleEmployee.json":{"language":"JSON","code":3,"comment":0,"blank":0},"file:///d%3A/%E4%BC%9A%E8%AE%AE%E5%AE%A4%E9%A2%84%E7%BA%A6%E7%B3%BB%E7%BB%9F/mini/app.js":{"language":"JavaScript","code":14,"comment":29,"blank":1},"file:///d%3A/%E4%BC%9A%E8%AE%AE%E5%AE%A4%E9%A2%84%E7%BA%A6%E7%B3%BB%E7%BB%9F/mini/pages/roomDetail2/roomDetail2.js":{"language":"JavaScript","code":549,"comment":211,"blank":42},"file:///d%3A/%E4%BC%9A%E8%AE%AE%E5%AE%A4%E9%A2%84%E7%BA%A6%E7%B3%BB%E7%BB%9F/mini/cloud/updateEmployeeInfo/package.json":{"language":"JSON","code":14,"comment":0,"blank":0},"file:///d%3A/%E4%BC%9A%E8%AE%AE%E5%AE%A4%E9%A2%84%E7%BA%A6%E7%B3%BB%E7%BB%9F/mini/pages/index/index.wxss":{"language":"CSS","code":67,"comment":5,"blank":7},"file:///d%3A/%E4%BC%9A%E8%AE%AE%E5%AE%A4%E9%A2%84%E7%BA%A6%E7%B3%BB%E7%BB%9F/mini/pages/conditionSearch/conditionSearch.wxss":{"language":"CSS","code":223,"comment":6,"blank":30},"file:///d%3A/%E4%BC%9A%E8%AE%AE%E5%AE%A4%E9%A2%84%E7%BA%A6%E7%B3%BB%E7%BB%9F/mini/cloud/updateEmployeeInfo/index.js":{"language":"JavaScript","code":19,"comment":2,"blank":2},"file:///d%3A/%E4%BC%9A%E8%AE%AE%E5%AE%A4%E9%A2%84%E7%BA%A6%E7%B3%BB%E7%BB%9F/mini/pages/roomDetail2/roomDetail2.wxss":{"language":"CSS","code":460,"comment":77,"blank":82},"file:///d%3A/%E4%BC%9A%E8%AE%AE%E5%AE%A4%E9%A2%84%E7%BA%A6%E7%B3%BB%E7%BB%9F/mini/pages/conditionSearch/conditionSearch.wxml":{"language":"wxml","code":55,"comment":20,"blank":0},"file:///d%3A/%E4%BC%9A%E8%AE%AE%E5%AE%A4%E9%A2%84%E7%BA%A6%E7%B3%BB%E7%BB%9F/mini/pages/index/index.wxml":{"language":"wxml","code":14,"comment":4,"blank":0},"file:///d%3A/%E4%BC%9A%E8%AE%AE%E5%AE%A4%E9%A2%84%E7%BA%A6%E7%B3%BB%E7%BB%9F/mini/pages/index/index.json":{"language":"JSON","code":3,"comment":0,"blank":0},"file:///d%3A/%E4%BC%9A%E8%AE%AE%E5%AE%A4%E9%A2%84%E7%BA%A6%E7%B3%BB%E7%BB%9F/mini/pages/handleEmployee/handleEmployee.js":{"language":"JavaScript","code":207,"comment":84,"blank":36},"file:///d%3A/%E4%BC%9A%E8%AE%AE%E5%AE%A4%E9%A2%84%E7%BA%A6%E7%B3%BB%E7%BB%9F/mini/pages/handleEmployee/handleEmployee.wxss":{"language":"CSS","code":141,"comment":14,"blank":20},"file:///d%3A/%E4%BC%9A%E8%AE%AE%E5%AE%A4%E9%A2%84%E7%BA%A6%E7%B3%BB%E7%BB%9F/mini/cloud/updateEmployeeInfo/config.json":{"language":"JSON","code":6,"comment":0,"blank":0},"file:///d%3A/%E4%BC%9A%E8%AE%AE%E5%AE%A4%E9%A2%84%E7%BA%A6%E7%B3%BB%E7%BB%9F/mini/pages/conditionSearch/conditionSearch.json":{"language":"JSON","code":3,"comment":0,"blank":0},"file:///d%3A/%E4%BC%9A%E8%AE%AE%E5%AE%A4%E9%A2%84%E7%BA%A6%E7%B3%BB%E7%BB%9F/mini/pages/conditionSearch/conditionSearch.js":{"language":"JavaScript","code":303,"comment":139,"blank":38},"file:///d%3A/%E4%BC%9A%E8%AE%AE%E5%AE%A4%E9%A2%84%E7%BA%A6%E7%B3%BB%E7%BB%9F/mini/pages/index/index.js":{"language":"JavaScript","code":227,"comment":212,"blank":36},"file:///d%3A/%E4%BC%9A%E8%AE%AE%E5%AE%A4%E9%A2%84%E7%BA%A6%E7%B3%BB%E7%BB%9F/mini/pages/showUserAppoint/showUserAppoint.wxss":{"language":"CSS","code":173,"comment":16,"blank":25},"file:///d%3A/%E4%BC%9A%E8%AE%AE%E5%AE%A4%E9%A2%84%E7%BA%A6%E7%B3%BB%E7%BB%9F/mini/pages/showUserAppoint/showUserAppoint.json":{"language":"JSON","code":9,"comment":0,"blank":0},"file:///d%3A/%E4%BC%9A%E8%AE%AE%E5%AE%A4%E9%A2%84%E7%BA%A6%E7%B3%BB%E7%BB%9F/mini/pages/showUserAppoint/showUserAppoint.js":{"language":"JavaScript","code":146,"comment":45,"blank":24},"file:///d%3A/%E4%BC%9A%E8%AE%AE%E5%AE%A4%E9%A2%84%E7%BA%A6%E7%B3%BB%E7%BB%9F/mini/pages/showUserAppoint/showUserAppoint.wxml":{"language":"wxml","code":84,"comment":34,"blank":0},"file:///d%3A/%E4%BC%9A%E8%AE%AE%E5%AE%A4%E9%A2%84%E7%BA%A6%E7%B3%BB%E7%BB%9F/mini/pages/user/user.wxml":{"language":"wxml","code":27,"comment":7,"blank":0},"file:///d%3A/%E4%BC%9A%E8%AE%AE%E5%AE%A4%E9%A2%84%E7%BA%A6%E7%B3%BB%E7%BB%9F/mini/pages/user/user.wxss":{"language":"CSS","code":145,"comment":7,"blank":17},"file:///d%3A/%E4%BC%9A%E8%AE%AE%E5%AE%A4%E9%A2%84%E7%BA%A6%E7%B3%BB%E7%BB%9F/mini/pages/user/user.json":{"language":"JSON","code":3,"comment":0,"blank":0},"file:///d%3A/%E4%BC%9A%E8%AE%AE%E5%AE%A4%E9%A2%84%E7%BA%A6%E7%B3%BB%E7%BB%9F/mini/pages/tourists/tourists.wxml":{"language":"wxml","code":28,"comment":7,"blank":0},"file:///d%3A/%E4%BC%9A%E8%AE%AE%E5%AE%A4%E9%A2%84%E7%BA%A6%E7%B3%BB%E7%BB%9F/mini/pages/user/user.js":{"language":"JavaScript","code":85,"comment":35,"blank":19},"file:///d%3A/%E4%BC%9A%E8%AE%AE%E5%AE%A4%E9%A2%84%E7%BA%A6%E7%B3%BB%E7%BB%9F/mini/pages/test/test.wxss":{"language":"CSS","code":8,"comment":1,"blank":0},"file:///d%3A/%E4%BC%9A%E8%AE%AE%E5%AE%A4%E9%A2%84%E7%BA%A6%E7%B3%BB%E7%BB%9F/mini/pages/tourists/tourists.wxss":{"language":"CSS","code":151,"comment":6,"blank":18},"file:///d%3A/%E4%BC%9A%E8%AE%AE%E5%AE%A4%E9%A2%84%E7%BA%A6%E7%B3%BB%E7%BB%9F/mini/pages/tourists/tourists.json":{"language":"JSON","code":3,"comment":0,"blank":0},"file:///d%3A/%E4%BC%9A%E8%AE%AE%E5%AE%A4%E9%A2%84%E7%BA%A6%E7%B3%BB%E7%BB%9F/mini/pages/test/test.wxml":{"language":"wxml","code":4,"comment":1,"blank":0},"file:///d%3A/%E4%BC%9A%E8%AE%AE%E5%AE%A4%E9%A2%84%E7%BA%A6%E7%B3%BB%E7%BB%9F/mini/pages/test/test.json":{"language":"JSON","code":3,"comment":0,"blank":0},"file:///d%3A/%E4%BC%9A%E8%AE%AE%E5%AE%A4%E9%A2%84%E7%BA%A6%E7%B3%BB%E7%BB%9F/mini/pages/test/test.js":{"language":"JavaScript","code":51,"comment":29,"blank":19},"file:///d%3A/%E4%BC%9A%E8%AE%AE%E5%AE%A4%E9%A2%84%E7%BA%A6%E7%B3%BB%E7%BB%9F/mini/pages/tourists/tourists.js":{"language":"JavaScript","code":158,"comment":46,"blank":23},"file:///d%3A/%E4%BC%9A%E8%AE%AE%E5%AE%A4%E9%A2%84%E7%BA%A6%E7%B3%BB%E7%BB%9F/mini/pages/studentRegistered/studentRegistered.wxss":{"language":"CSS","code":63,"comment":4,"blank":8},"file:///d%3A/%E4%BC%9A%E8%AE%AE%E5%AE%A4%E9%A2%84%E7%BA%A6%E7%B3%BB%E7%BB%9F/mini/pages/studentRegistered/studentRegistered.wxml":{"language":"wxml","code":45,"comment":10,"blank":1},"file:///d%3A/%E4%BC%9A%E8%AE%AE%E5%AE%A4%E9%A2%84%E7%BA%A6%E7%B3%BB%E7%BB%9F/mini/pages/studentRegistered/studentRegistered.json":{"language":"JSON","code":3,"comment":0,"blank":0},"file:///d%3A/%E4%BC%9A%E8%AE%AE%E5%AE%A4%E9%A2%84%E7%BA%A6%E7%B3%BB%E7%BB%9F/mini/pages/studentRegistered/studentRegistered.js":{"language":"JavaScript","code":170,"comment":58,"blank":25},"file:///d%3A/%E4%BC%9A%E8%AE%AE%E5%AE%A4%E9%A2%84%E7%BA%A6%E7%B3%BB%E7%BB%9F/mini/cloud/updateUserAppointInfo/package.json":{"language":"JSON","code":14,"comment":0,"blank":0},"file:///d%3A/%E4%BC%9A%E8%AE%AE%E5%AE%A4%E9%A2%84%E7%BA%A6%E7%B3%BB%E7%BB%9F/mini/cloud/updateUserAppointInfo/index.js":{"language":"JavaScript","code":13,"comment":2,"blank":2},"file:///d%3A/%E4%BC%9A%E8%AE%AE%E5%AE%A4%E9%A2%84%E7%BA%A6%E7%B3%BB%E7%BB%9F/mini/cloud/updateUserAppointInfo/config.json":{"language":"JSON","code":6,"comment":0,"blank":0},"file:///d%3A/%E4%BC%9A%E8%AE%AE%E5%AE%A4%E9%A2%84%E7%BA%A6%E7%B3%BB%E7%BB%9F/mini/pages/teacherRegistered/teacherRegistered.json":{"language":"JSON","code":3,"comment":0,"blank":0},"file:///d%3A/%E4%BC%9A%E8%AE%AE%E5%AE%A4%E9%A2%84%E7%BA%A6%E7%B3%BB%E7%BB%9F/mini/pages/teacherRegistered/teacherRegistered.wxml":{"language":"wxml","code":34,"comment":8,"blank":2},"file:///d%3A/%E4%BC%9A%E8%AE%AE%E5%AE%A4%E9%A2%84%E7%BA%A6%E7%B3%BB%E7%BB%9F/mini/pages/teacherRegistered/teacherRegistered.wxss":{"language":"CSS","code":62,"comment":4,"blank":8},"file:///d%3A/%E4%BC%9A%E8%AE%AE%E5%AE%A4%E9%A2%84%E7%BA%A6%E7%B3%BB%E7%BB%9F/mini/pages/showRoomQrimg/showRoomQrimg.wxss":{"language":"CSS","code":30,"comment":5,"blank":4},"file:///d%3A/%E4%BC%9A%E8%AE%AE%E5%AE%A4%E9%A2%84%E7%BA%A6%E7%B3%BB%E7%BB%9F/mini/pages/showRoomQrimg/showRoomQrimg.wxml":{"language":"wxml","code":11,"comment":2,"blank":0},"file:///d%3A/%E4%BC%9A%E8%AE%AE%E5%AE%A4%E9%A2%84%E7%BA%A6%E7%B3%BB%E7%BB%9F/mini/pages/showRoomQrimg/showRoomQrimg.json":{"language":"JSON","code":3,"comment":0,"blank":0},"file:///d%3A/%E4%BC%9A%E8%AE%AE%E5%AE%A4%E9%A2%84%E7%BA%A6%E7%B3%BB%E7%BB%9F/mini/pages/showRoomQrimg/showRoomQrimg.js":{"language":"JavaScript","code":36,"comment":28,"blank":16},"file:///d%3A/%E4%BC%9A%E8%AE%AE%E5%AE%A4%E9%A2%84%E7%BA%A6%E7%B3%BB%E7%BB%9F/mini/pages/teacherRegistered/teacherRegistered.js":{"language":"JavaScript","code":151,"comment":41,"blank":21},"file:///d%3A/%E4%BC%9A%E8%AE%AE%E5%AE%A4%E9%A2%84%E7%BA%A6%E7%B3%BB%E7%BB%9F/mini/pages/showRoomInfo/showRoomInfo.wxss":{"language":"CSS","code":80,"comment":5,"blank":10},"file:///d%3A/%E4%BC%9A%E8%AE%AE%E5%AE%A4%E9%A2%84%E7%BA%A6%E7%B3%BB%E7%BB%9F/mini/pages/roomsEdit/roomsEdit.wxss":{"language":"CSS","code":352,"comment":30,"blank":46},"file:///d%3A/%E4%BC%9A%E8%AE%AE%E5%AE%A4%E9%A2%84%E7%BA%A6%E7%B3%BB%E7%BB%9F/mini/pages/showRoomInfo/showRoomInfo.wxml":{"language":"wxml","code":34,"comment":1,"blank":0},"file:///d%3A/%E4%BC%9A%E8%AE%AE%E5%AE%A4%E9%A2%84%E7%BA%A6%E7%B3%BB%E7%BB%9F/mini/pages/roomsEdit/roomsEdit.json":{"language":"JSON","code":5,"comment":0,"blank":0},"file:///d%3A/%E4%BC%9A%E8%AE%AE%E5%AE%A4%E9%A2%84%E7%BA%A6%E7%B3%BB%E7%BB%9F/mini/pages/showRoomInfo/showRoomInfo.json":{"language":"JSON","code":3,"comment":0,"blank":0},"file:///d%3A/%E4%BC%9A%E8%AE%AE%E5%AE%A4%E9%A2%84%E7%BA%A6%E7%B3%BB%E7%BB%9F/mini/pages/showRoomInfo/showRoomInfo.js":{"language":"JavaScript","code":76,"comment":33,"blank":18},"file:///d%3A/%E4%BC%9A%E8%AE%AE%E5%AE%A4%E9%A2%84%E7%BA%A6%E7%B3%BB%E7%BB%9F/mini/pages/roomsEdit/roomsEdit.wxml":{"language":"wxml","code":53,"comment":13,"blank":0},"file:///d%3A/%E4%BC%9A%E8%AE%AE%E5%AE%A4%E9%A2%84%E7%BA%A6%E7%B3%BB%E7%BB%9F/mini/cloud/updateStudentInfo/package.json":{"language":"JSON","code":14,"comment":0,"blank":0},"file:///d%3A/%E4%BC%9A%E8%AE%AE%E5%AE%A4%E9%A2%84%E7%BA%A6%E7%B3%BB%E7%BB%9F/mini/pages/roomsEdit/roomsEdit.js":{"language":"JavaScript","code":436,"comment":102,"blank":38},"file:///d%3A/%E4%BC%9A%E8%AE%AE%E5%AE%A4%E9%A2%84%E7%BA%A6%E7%B3%BB%E7%BB%9F/mini/cloud/updateSTInfo/package.json":{"language":"JSON","code":14,"comment":0,"blank":0},"file:///d%3A/%E4%BC%9A%E8%AE%AE%E5%AE%A4%E9%A2%84%E7%BA%A6%E7%B3%BB%E7%BB%9F/mini/cloud/updateSTInfo/index.js":{"language":"JavaScript","code":13,"comment":2,"blank":2},"file:///d%3A/%E4%BC%9A%E8%AE%AE%E5%AE%A4%E9%A2%84%E7%BA%A6%E7%B3%BB%E7%BB%9F/mini/pages/roleChoose/roleChoose.json":{"language":"JSON","code":3,"comment":0,"blank":0},"file:///d%3A/%E4%BC%9A%E8%AE%AE%E5%AE%A4%E9%A2%84%E7%BA%A6%E7%B3%BB%E7%BB%9F/mini/pages/roleChoose/roleChoose.js":{"language":"JavaScript","code":148,"comment":40,"blank":22},"file:///d%3A/%E4%BC%9A%E8%AE%AE%E5%AE%A4%E9%A2%84%E7%BA%A6%E7%B3%BB%E7%BB%9F/mini/cloud/updateStudentInfo/index.js":{"language":"JavaScript","code":20,"comment":2,"blank":2},"file:///d%3A/%E4%BC%9A%E8%AE%AE%E5%AE%A4%E9%A2%84%E7%BA%A6%E7%B3%BB%E7%BB%9F/mini/cloud/updateTeacherInfo/package.json":{"language":"JSON","code":14,"comment":0,"blank":0},"file:///d%3A/%E4%BC%9A%E8%AE%AE%E5%AE%A4%E9%A2%84%E7%BA%A6%E7%B3%BB%E7%BB%9F/mini/cloud/updateTeacherInfo/index.js":{"language":"JavaScript","code":18,"comment":2,"blank":2},"file:///d%3A/%E4%BC%9A%E8%AE%AE%E5%AE%A4%E9%A2%84%E7%BA%A6%E7%B3%BB%E7%BB%9F/mini/cloud/updateStudentInfo/config.json":{"language":"JSON","code":6,"comment":0,"blank":0},"file:///d%3A/%E4%BC%9A%E8%AE%AE%E5%AE%A4%E9%A2%84%E7%BA%A6%E7%B3%BB%E7%BB%9F/mini/cloud/addRoomAppointInfo/package.json":{"language":"JSON","code":14,"comment":0,"blank":0},"file:///d%3A/%E4%BC%9A%E8%AE%AE%E5%AE%A4%E9%A2%84%E7%BA%A6%E7%B3%BB%E7%BB%9F/mini/cloud/updateSTInfo/config.json":{"language":"JSON","code":6,"comment":0,"blank":0},"file:///d%3A/%E4%BC%9A%E8%AE%AE%E5%AE%A4%E9%A2%84%E7%BA%A6%E7%B3%BB%E7%BB%9F/mini/cloud/updateTeacherInfo/config.json":{"language":"JSON","code":6,"comment":0,"blank":0},"file:///d%3A/%E4%BC%9A%E8%AE%AE%E5%AE%A4%E9%A2%84%E7%BA%A6%E7%B3%BB%E7%BB%9F/mini/pages/roleChoose/roleChoose.wxml":{"language":"wxml","code":13,"comment":1,"blank":1},"file:///d%3A/%E4%BC%9A%E8%AE%AE%E5%AE%A4%E9%A2%84%E7%BA%A6%E7%B3%BB%E7%BB%9F/mini/cloud/addRoomAppointInfo/config.json":{"language":"JSON","code":6,"comment":0,"blank":0},"file:///d%3A/%E4%BC%9A%E8%AE%AE%E5%AE%A4%E9%A2%84%E7%BA%A6%E7%B3%BB%E7%BB%9F/mini/cloud/addRoomAppointInfo/index.js":{"language":"JavaScript","code":11,"comment":2,"blank":3},"file:///d%3A/%E4%BC%9A%E8%AE%AE%E5%AE%A4%E9%A2%84%E7%BA%A6%E7%B3%BB%E7%BB%9F/mini/pages/roomDetail/roomDetail.wxss":{"language":"CSS","code":420,"comment":88,"blank":74},"file:///d%3A/%E4%BC%9A%E8%AE%AE%E5%AE%A4%E9%A2%84%E7%BA%A6%E7%B3%BB%E7%BB%9F/mini/pages/roomDetail/roomDetail.wxml":{"language":"wxml","code":170,"comment":29,"blank":1},"file:///d%3A/%E4%BC%9A%E8%AE%AE%E5%AE%A4%E9%A2%84%E7%BA%A6%E7%B3%BB%E7%BB%9F/mini/pages/roleChoose/roleChoose.wxss":{"language":"CSS","code":33,"comment":1,"blank":5},"file:///d%3A/%E4%BC%9A%E8%AE%AE%E5%AE%A4%E9%A2%84%E7%BA%A6%E7%B3%BB%E7%BB%9F/mini/pages/roomDetail/roomDetail.json":{"language":"JSON","code":5,"comment":0,"blank":0},"file:///d%3A/%E4%BC%9A%E8%AE%AE%E5%AE%A4%E9%A2%84%E7%BA%A6%E7%B3%BB%E7%BB%9F/mini/cloud/updateRoomInfo/package.json":{"language":"JSON","code":14,"comment":0,"blank":0},"file:///d%3A/%E4%BC%9A%E8%AE%AE%E5%AE%A4%E9%A2%84%E7%BA%A6%E7%B3%BB%E7%BB%9F/mini/cloud/updateRoomInfo/index.js":{"language":"JavaScript","code":27,"comment":2,"blank":2},"file:///d%3A/%E4%BC%9A%E8%AE%AE%E5%AE%A4%E9%A2%84%E7%BA%A6%E7%B3%BB%E7%BB%9F/mini/cloud/addTeacher/package.json":{"language":"JSON","code":14,"comment":0,"blank":0},"file:///d%3A/%E4%BC%9A%E8%AE%AE%E5%AE%A4%E9%A2%84%E7%BA%A6%E7%B3%BB%E7%BB%9F/mini/cloud/updateRoomInfo/config.json":{"language":"JSON","code":6,"comment":0,"blank":0},"file:///d%3A/%E4%BC%9A%E8%AE%AE%E5%AE%A4%E9%A2%84%E7%BA%A6%E7%B3%BB%E7%BB%9F/mini/cloud/addTeacher/index.js":{"language":"JavaScript","code":17,"comment":2,"blank":2},"file:///d%3A/%E4%BC%9A%E8%AE%AE%E5%AE%A4%E9%A2%84%E7%BA%A6%E7%B3%BB%E7%BB%9F/mini/cloud/updateRoomAppointInfo/package.json":{"language":"JSON","code":14,"comment":0,"blank":0},"file:///d%3A/%E4%BC%9A%E8%AE%AE%E5%AE%A4%E9%A2%84%E7%BA%A6%E7%B3%BB%E7%BB%9F/mini/pages/roomDetail/roomDetail.js":{"language":"JavaScript","code":1086,"comment":229,"blank":82},"file:///d%3A/%E4%BC%9A%E8%AE%AE%E5%AE%A4%E9%A2%84%E7%BA%A6%E7%B3%BB%E7%BB%9F/mini/cloud/getRoomInfo/config.json":{"language":"JSON","code":6,"comment":0,"blank":0},"file:///d%3A/%E4%BC%9A%E8%AE%AE%E5%AE%A4%E9%A2%84%E7%BA%A6%E7%B3%BB%E7%BB%9F/mini/pages/registered/registered.js":{"language":"JavaScript","code":249,"comment":60,"blank":26},"file:///d%3A/%E4%BC%9A%E8%AE%AE%E5%AE%A4%E9%A2%84%E7%BA%A6%E7%B3%BB%E7%BB%9F/mini/cloud/updateRoomAppointInfo/config.json":{"language":"JSON","code":6,"comment":0,"blank":0},"file:///d%3A/%E4%BC%9A%E8%AE%AE%E5%AE%A4%E9%A2%84%E7%BA%A6%E7%B3%BB%E7%BB%9F/mini/cloud/updateRoomAppointInfo/index.js":{"language":"JavaScript","code":13,"comment":7,"blank":2},"file:///d%3A/%E4%BC%9A%E8%AE%AE%E5%AE%A4%E9%A2%84%E7%BA%A6%E7%B3%BB%E7%BB%9F/mini/cloud/getRoomInfo/index.js":{"language":"JavaScript","code":6,"comment":2,"blank":2},"file:///d%3A/%E4%BC%9A%E8%AE%AE%E5%AE%A4%E9%A2%84%E7%BA%A6%E7%B3%BB%E7%BB%9F/mini/pages/registered/registered.json":{"language":"JSON","code":3,"comment":0,"blank":0},"file:///d%3A/%E4%BC%9A%E8%AE%AE%E5%AE%A4%E9%A2%84%E7%BA%A6%E7%B3%BB%E7%BB%9F/mini/cloud/addTeacher/config.json":{"language":"JSON","code":6,"comment":0,"blank":0},"file:///d%3A/%E4%BC%9A%E8%AE%AE%E5%AE%A4%E9%A2%84%E7%BA%A6%E7%B3%BB%E7%BB%9F/mini/cloud/getOpenId/package.json":{"language":"JSON","code":14,"comment":0,"blank":0},"file:///d%3A/%E4%BC%9A%E8%AE%AE%E5%AE%A4%E9%A2%84%E7%BA%A6%E7%B3%BB%E7%BB%9F/mini/cloud/getOpenId/index.js":{"language":"JavaScript","code":11,"comment":2,"blank":3},"file:///d%3A/%E4%BC%9A%E8%AE%AE%E5%AE%A4%E9%A2%84%E7%BA%A6%E7%B3%BB%E7%BB%9F/mini/pages/newAppointment/newAppointment.wxss":{"language":"CSS","code":159,"comment":15,"blank":25},"file:///d%3A/%E4%BC%9A%E8%AE%AE%E5%AE%A4%E9%A2%84%E7%BA%A6%E7%B3%BB%E7%BB%9F/mini/pages/newAppointment/newAppointment.wxml":{"language":"wxml","code":52,"comment":11,"blank":1},"file:///d%3A/%E4%BC%9A%E8%AE%AE%E5%AE%A4%E9%A2%84%E7%BA%A6%E7%B3%BB%E7%BB%9F/mini/cloud/getOpenId/config.json":{"language":"JSON","code":6,"comment":0,"blank":0},"file:///d%3A/%E4%BC%9A%E8%AE%AE%E5%AE%A4%E9%A2%84%E7%BA%A6%E7%B3%BB%E7%BB%9F/mini/cloud/getDateAppointList/config.json":{"language":"JSON","code":6,"comment":0,"blank":0},"file:///d%3A/%E4%BC%9A%E8%AE%AE%E5%AE%A4%E9%A2%84%E7%BA%A6%E7%B3%BB%E7%BB%9F/mini/pages/newAppointment/newAppointment.js":{"language":"JavaScript","code":503,"comment":280,"blank":45},"file:///d%3A/%E4%BC%9A%E8%AE%AE%E5%AE%A4%E9%A2%84%E7%BA%A6%E7%B3%BB%E7%BB%9F/mini/cloud/getRoomInfo/package.json":{"language":"JSON","code":14,"comment":0,"blank":0},"file:///d%3A/%E4%BC%9A%E8%AE%AE%E5%AE%A4%E9%A2%84%E7%BA%A6%E7%B3%BB%E7%BB%9F/mini/pages/registered/registered.wxss":{"language":"CSS","code":62,"comment":4,"blank":8},"file:///d%3A/%E4%BC%9A%E8%AE%AE%E5%AE%A4%E9%A2%84%E7%BA%A6%E7%B3%BB%E7%BB%9F/mini/pages/registered/registered.wxml":{"language":"wxml","code":40,"comment":9,"blank":0},"file:///d%3A/%E4%BC%9A%E8%AE%AE%E5%AE%A4%E9%A2%84%E7%BA%A6%E7%B3%BB%E7%BB%9F/mini/cloud/getDateAppointList/index.js":{"language":"JavaScript","code":9,"comment":7,"blank":3},"file:///d%3A/%E4%BC%9A%E8%AE%AE%E5%AE%A4%E9%A2%84%E7%BA%A6%E7%B3%BB%E7%BB%9F/mini/cloud/generateQr/package.json":{"language":"JSON","code":14,"comment":0,"blank":0},"file:///d%3A/%E4%BC%9A%E8%AE%AE%E5%AE%A4%E9%A2%84%E7%BA%A6%E7%B3%BB%E7%BB%9F/mini/cloud/getDateAppointList/package.json":{"language":"JSON","code":14,"comment":0,"blank":0},"file:///d%3A/%E4%BC%9A%E8%AE%AE%E5%AE%A4%E9%A2%84%E7%BA%A6%E7%B3%BB%E7%BB%9F/mini/cloud/generateQr/index.js":{"language":"JavaScript","code":18,"comment":4,"blank":2},"file:///d%3A/%E4%BC%9A%E8%AE%AE%E5%AE%A4%E9%A2%84%E7%BA%A6%E7%B3%BB%E7%BB%9F/mini/pages/newAppointment/newAppointment.json":{"language":"JSON","code":3,"comment":0,"blank":0},"file:///d%3A/%E4%BC%9A%E8%AE%AE%E5%AE%A4%E9%A2%84%E7%BA%A6%E7%B3%BB%E7%BB%9F/mini/cloud/generateQr/config.json":{"language":"JSON","code":6,"comment":0,"blank":0},"file:///d%3A/%E4%BC%9A%E8%AE%AE%E5%AE%A4%E9%A2%84%E7%BA%A6%E7%B3%BB%E7%BB%9F/mini/cloud/delTeacherInfo/package.json":{"language":"JSON","code":14,"comment":0,"blank":0},"file:///d%3A/%E4%BC%9A%E8%AE%AE%E5%AE%A4%E9%A2%84%E7%BA%A6%E7%B3%BB%E7%BB%9F/mini/cloud/delTeacherInfo/index.js":{"language":"JavaScript","code":9,"comment":2,"blank":2},"file:///d%3A/%E4%BC%9A%E8%AE%AE%E5%AE%A4%E9%A2%84%E7%BA%A6%E7%B3%BB%E7%BB%9F/mini/cloud/delTeacherInfo/config.json":{"language":"JSON","code":6,"comment":0,"blank":0},"file:///d%3A/%E4%BC%9A%E8%AE%AE%E5%AE%A4%E9%A2%84%E7%BA%A6%E7%B3%BB%E7%BB%9F/mini/cloud/delRoomInfoItem/package.json":{"language":"JSON","code":14,"comment":0,"blank":0},"file:///d%3A/%E4%BC%9A%E8%AE%AE%E5%AE%A4%E9%A2%84%E7%BA%A6%E7%B3%BB%E7%BB%9F/mini/cloud/delRoomInfoItem/index.js":{"language":"JavaScript","code":9,"comment":2,"blank":2},"file:///d%3A/%E4%BC%9A%E8%AE%AE%E5%AE%A4%E9%A2%84%E7%BA%A6%E7%B3%BB%E7%BB%9F/mini/cloud/delRoomInfoItem/config.json":{"language":"JSON","code":6,"comment":0,"blank":0},"file:///d%3A/%E4%BC%9A%E8%AE%AE%E5%AE%A4%E9%A2%84%E7%BA%A6%E7%B3%BB%E7%BB%9F/mini/cloud/delStudentInfo/package.json":{"language":"JSON","code":14,"comment":0,"blank":0},"file:///d%3A/%E4%BC%9A%E8%AE%AE%E5%AE%A4%E9%A2%84%E7%BA%A6%E7%B3%BB%E7%BB%9F/mini/cloud/delStudentInfo/index.js":{"language":"JavaScript","code":9,"comment":2,"blank":2},"file:///d%3A/%E4%BC%9A%E8%AE%AE%E5%AE%A4%E9%A2%84%E7%BA%A6%E7%B3%BB%E7%BB%9F/mini/pages/jobFair/jobFair.wxml":{"language":"wxml","code":1,"comment":1,"blank":1},"file:///d%3A/%E4%BC%9A%E8%AE%AE%E5%AE%A4%E9%A2%84%E7%BA%A6%E7%B3%BB%E7%BB%9F/mini/cloud/delStudentInfo/config.json":{"language":"JSON","code":6,"comment":0,"blank":0},"file:///d%3A/%E4%BC%9A%E8%AE%AE%E5%AE%A4%E9%A2%84%E7%BA%A6%E7%B3%BB%E7%BB%9F/mini/pages/jobFair/jobFair.js":{"language":"JavaScript","code":20,"comment":28,"blank":18},"file:///d%3A/%E4%BC%9A%E8%AE%AE%E5%AE%A4%E9%A2%84%E7%BA%A6%E7%B3%BB%E7%BB%9F/mini/static/iconfont/iconfont.wxss":{"language":"CSS","code":40,"comment":1,"blank":10},"file:///d%3A/%E4%BC%9A%E8%AE%AE%E5%AE%A4%E9%A2%84%E7%BA%A6%E7%B3%BB%E7%BB%9F/mini/pages/handleAppointItem/handleAppointItem.js":{"language":"JavaScript","code":301,"comment":81,"blank":26},"file:///d%3A/%E4%BC%9A%E8%AE%AE%E5%AE%A4%E9%A2%84%E7%BA%A6%E7%B3%BB%E7%BB%9F/mini/pages/handleAppointItem/handleAppointItem.json":{"language":"JSON","code":9,"comment":0,"blank":0},"file:///d%3A/%E4%BC%9A%E8%AE%AE%E5%AE%A4%E9%A2%84%E7%BA%A6%E7%B3%BB%E7%BB%9F/mini/pages/appointedEdit/appointedEdit.wxml":{"language":"wxml","code":68,"comment":21,"blank":0},"file:///d%3A/%E4%BC%9A%E8%AE%AE%E5%AE%A4%E9%A2%84%E7%BA%A6%E7%B3%BB%E7%BB%9F/mini/pages/appointedEdit/appointedEdit.js":{"language":"JavaScript","code":337,"comment":69,"blank":35},"file:///d%3A/%E4%BC%9A%E8%AE%AE%E5%AE%A4%E9%A2%84%E7%BA%A6%E7%B3%BB%E7%BB%9F/mini/pages/appointedEdit/appointedEdit.wxss":{"language":"CSS","code":172,"comment":17,"blank":27},"file:///d%3A/%E4%BC%9A%E8%AE%AE%E5%AE%A4%E9%A2%84%E7%BA%A6%E7%B3%BB%E7%BB%9F/mini/pages/handleAppointItem/handleAppointItem.wxss":{"language":"CSS","code":160,"comment":14,"blank":25},"file:///d%3A/%E4%BC%9A%E8%AE%AE%E5%AE%A4%E9%A2%84%E7%BA%A6%E7%B3%BB%E7%BB%9F/mini/pages/appointedEdit/appointedEdit.json":{"language":"JSON","code":3,"comment":0,"blank":0},"file:///d%3A/%E4%BC%9A%E8%AE%AE%E5%AE%A4%E9%A2%84%E7%BA%A6%E7%B3%BB%E7%BB%9F/mini/pages/admin/admin.json":{"language":"JSON","code":3,"comment":0,"blank":0},"file:///d%3A/%E4%BC%9A%E8%AE%AE%E5%AE%A4%E9%A2%84%E7%BA%A6%E7%B3%BB%E7%BB%9F/mini/pages/handleAppointItem/handleAppointItem.wxml":{"language":"wxml","code":33,"comment":9,"blank":0},"file:///d%3A/%E4%BC%9A%E8%AE%AE%E5%AE%A4%E9%A2%84%E7%BA%A6%E7%B3%BB%E7%BB%9F/mini/pages/admin/admin.wxml":{"language":"wxml","code":32,"comment":8,"blank":0},"file:///d%3A/%E4%BC%9A%E8%AE%AE%E5%AE%A4%E9%A2%84%E7%BA%A6%E7%B3%BB%E7%BB%9F/mini/pages/admin/admin.js":{"language":"JavaScript","code":43,"comment":32,"blank":18},"file:///d%3A/%E4%BC%9A%E8%AE%AE%E5%AE%A4%E9%A2%84%E7%BA%A6%E7%B3%BB%E7%BB%9F/mini/pages/admin/admin.wxss":{"language":"CSS","code":145,"comment":6,"blank":17},"file:///d%3A/%E4%BC%9A%E8%AE%AE%E5%AE%A4%E9%A2%84%E7%BA%A6%E7%B3%BB%E7%BB%9F/mini/data/%E6%95%B0%E6%8D%AE2.csv":{"language":"CSV","code":3,"comment":0,"blank":1},"file:///d%3A/%E4%BC%9A%E8%AE%AE%E5%AE%A4%E9%A2%84%E7%BA%A6%E7%B3%BB%E7%BB%9F/mini/data/%E5%AF%BC%E5%85%A5%E6%95%B0%E6%8D%AE%E5%BA%93%E7%9A%84%E6%93%8D%E4%BD%9C.md":{"language":"Markdown","code":7,"comment":0,"blank":1},"file:///d%3A/%E4%BC%9A%E8%AE%AE%E5%AE%A4%E9%A2%84%E7%BA%A6%E7%B3%BB%E7%BB%9F/mini/data/%E4%BC%81%E4%B8%9A%E5%91%98%E5%B7%A5%E6%95%B0%E6%8D%AE1.json":{"language":"JSON","code":109,"comment":0,"blank":0},"file:///d%3A/%E4%BC%9A%E8%AE%AE%E5%AE%A4%E9%A2%84%E7%BA%A6%E7%B3%BB%E7%BB%9F/mini/data/database_export-xOrd9Kwrd7yQ.json":{"language":"JSON","code":29,"comment":0,"blank":1},"file:///d%3A/%E4%BC%9A%E8%AE%AE%E5%AE%A4%E9%A2%84%E7%BA%A6%E7%B3%BB%E7%BB%9F/mini/data/roomInfo.csv":{"language":"CSV","code":14,"comment":0,"blank":0},"file:///d%3A/%E4%BC%9A%E8%AE%AE%E5%AE%A4%E9%A2%84%E7%BA%A6%E7%B3%BB%E7%BB%9F/mini/data/database_export-jCSnnFqZD4QN.json":{"language":"JSON","code":2,"comment":0,"blank":1},"file:///d%3A/%E4%BC%9A%E8%AE%AE%E5%AE%A4%E9%A2%84%E7%BA%A6%E7%B3%BB%E7%BB%9F/mini/data/database_export-FCV1Dkr1H5NW.json":{"language":"JSON","code":87,"comment":0,"blank":0},"file:///d%3A/%E4%BC%9A%E8%AE%AE%E5%AE%A4%E9%A2%84%E7%BA%A6%E7%B3%BB%E7%BB%9F/mini/data/database_export-ikOxH1JeBDPt.csv":{"language":"CSV","code":3,"comment":0,"blank":1},"file:///d%3A/%E4%BC%9A%E8%AE%AE%E5%AE%A4%E9%A2%84%E7%BA%A6%E7%B3%BB%E7%BB%9F/mini/.idea/vcs.xml":{"language":"XML","code":6,"comment":0,"blank":0},"file:///d%3A/%E4%BC%9A%E8%AE%AE%E5%AE%A4%E9%A2%84%E7%BA%A6%E7%B3%BB%E7%BB%9F/mini/data/database_export-7HAwf_mruPjd.json":{"language":"JSON","code":12,"comment":0,"blank":1},"file:///d%3A/%E4%BC%9A%E8%AE%AE%E5%AE%A4%E9%A2%84%E7%BA%A6%E7%B3%BB%E7%BB%9F/mini/.idea/roomAppointment.iml":{"language":"XML","code":12,"comment":0,"blank":0},"file:///d%3A/%E4%BC%9A%E8%AE%AE%E5%AE%A4%E9%A2%84%E7%BA%A6%E7%B3%BB%E7%BB%9F/mini/pages/addRoom/addRoom.wxss":{"language":"CSS","code":225,"comment":32,"blank":30},"file:///d%3A/%E4%BC%9A%E8%AE%AE%E5%AE%A4%E9%A2%84%E7%BA%A6%E7%B3%BB%E7%BB%9F/mini/pages/addRoom/addRoom.wxml":{"language":"wxml","code":67,"comment":13,"blank":0},"file:///d%3A/%E4%BC%9A%E8%AE%AE%E5%AE%A4%E9%A2%84%E7%BA%A6%E7%B3%BB%E7%BB%9F/mini/pages/addRoom/addRoom.json":{"language":"JSON","code":6,"comment":0,"blank":0},"file:///d%3A/%E4%BC%9A%E8%AE%AE%E5%AE%A4%E9%A2%84%E7%BA%A6%E7%B3%BB%E7%BB%9F/mini/cloud/delEmployeeInfo/package.json":{"language":"JSON","code":14,"comment":0,"blank":0},"file:///d%3A/%E4%BC%9A%E8%AE%AE%E5%AE%A4%E9%A2%84%E7%BA%A6%E7%B3%BB%E7%BB%9F/mini/cloud/delEmployeeInfo/index.js":{"language":"JavaScript","code":9,"comment":2,"blank":2},"file:///d%3A/%E4%BC%9A%E8%AE%AE%E5%AE%A4%E9%A2%84%E7%BA%A6%E7%B3%BB%E7%BB%9F/mini/pages/addRoom/addRoom.js":{"language":"JavaScript","code":501,"comment":105,"blank":46},"file:///d%3A/%E4%BC%9A%E8%AE%AE%E5%AE%A4%E9%A2%84%E7%BA%A6%E7%B3%BB%E7%BB%9F/mini/cloud/delEmployeeInfo/config.json":{"language":"JSON","code":6,"comment":0,"blank":0},"file:///d%3A/%E4%BC%9A%E8%AE%AE%E5%AE%A4%E9%A2%84%E7%BA%A6%E7%B3%BB%E7%BB%9F/mini/cloud/addUserAppoint/package.json":{"language":"JSON","code":14,"comment":0,"blank":0},"file:///d%3A/%E4%BC%9A%E8%AE%AE%E5%AE%A4%E9%A2%84%E7%BA%A6%E7%B3%BB%E7%BB%9F/mini/cloud/addUserAppoint/config.json":{"language":"JSON","code":6,"comment":0,"blank":0},"file:///d%3A/%E4%BC%9A%E8%AE%AE%E5%AE%A4%E9%A2%84%E7%BA%A6%E7%B3%BB%E7%BB%9F/mini/cloud/addUserAppoint/index.js":{"language":"JavaScript","code":11,"comment":2,"blank":2},"file:///d%3A/%E4%BC%9A%E8%AE%AE%E5%AE%A4%E9%A2%84%E7%BA%A6%E7%B3%BB%E7%BB%9F/mini/cloud/addStudent/package.json":{"language":"JSON","code":14,"comment":0,"blank":0},"file:///d%3A/%E4%BC%9A%E8%AE%AE%E5%AE%A4%E9%A2%84%E7%BA%A6%E7%B3%BB%E7%BB%9F/mini/cloud/addStudent/config.json":{"language":"JSON","code":6,"comment":0,"blank":0},"file:///d%3A/%E4%BC%9A%E8%AE%AE%E5%AE%A4%E9%A2%84%E7%BA%A6%E7%B3%BB%E7%BB%9F/mini/cloud/addRoomInfo/config.json":{"language":"JSON","code":6,"comment":0,"blank":0},"file:///d%3A/%E4%BC%9A%E8%AE%AE%E5%AE%A4%E9%A2%84%E7%BA%A6%E7%B3%BB%E7%BB%9F/mini/cloud/addStudent/index.js":{"language":"JavaScript","code":19,"comment":2,"blank":2},"file:///d%3A/%E4%BC%9A%E8%AE%AE%E5%AE%A4%E9%A2%84%E7%BA%A6%E7%B3%BB%E7%BB%9F/mini/cloud/addEmployee/index.js":{"language":"JavaScript","code":17,"comment":2,"blank":3},"file:///d%3A/%E4%BC%9A%E8%AE%AE%E5%AE%A4%E9%A2%84%E7%BA%A6%E7%B3%BB%E7%BB%9F/mini/cloud/addEmployee/package.json":{"language":"JSON","code":14,"comment":0,"blank":0},"file:///d%3A/%E4%BC%9A%E8%AE%AE%E5%AE%A4%E9%A2%84%E7%BA%A6%E7%B3%BB%E7%BB%9F/mini/cloud/addEmployee/config.json":{"language":"JSON","code":6,"comment":0,"blank":0},"file:///d%3A/%E4%BC%9A%E8%AE%AE%E5%AE%A4%E9%A2%84%E7%BA%A6%E7%B3%BB%E7%BB%9F/mini/cloud/addRoomInfo/index.js":{"language":"JavaScript","code":18,"comment":2,"blank":2},"file:///d%3A/%E4%BC%9A%E8%AE%AE%E5%AE%A4%E9%A2%84%E7%BA%A6%E7%B3%BB%E7%BB%9F/mini/cloud/addRoomInfo/package.json":{"language":"JSON","code":14,"comment":0,"blank":0}}